SWAMPE/__init__.py
SWAMPE/continuation.py
SWAMPE/explicit_tdiff.py
SWAMPE/filters.py
SWAMPE/forcing.py
SWAMPE/initial_conditions.py
SWAMPE/main_function.py
SWAMPE/modEuler_tdiff.py
SWAMPE/model.py
SWAMPE/plotting.py
SWAMPE/spectral_transform.py
SWAMPE/test_unit.py
SWAMPE/time_stepping.py
SWAMPE-1.0.0.dist-info/LICENCE.txt
SWAMPE-1.0.0.dist-info/METADATA
SWAMPE-1.0.0.dist-info/WHEEL
SWAMPE-1.0.0.dist-info/top_level.txt
SWAMPE-1.0.0.dist-info/RECORD
