Metadata-Version: 2.1
Name: SWAMPE
Version: 1.0.0
Summary: 2D Shallow-Water General Circulation Model for Exoplanet Atmospheres
Home-page: UNKNOWN
Author: Ekaterina Landgren
Author-email: ek672@cornell.edu
License: BSD 3-Clause License
Platform: UNKNOWN
Requires-Dist: numpy
Requires-Dist: scipy
Requires-Dist: imageio
Requires-Dist: matplotlib
Requires-Dist: jupyter
